static_import_analysis.py
static_import_analysis-0.1.0a0.dist-info/licenses/LICENSE
static_import_analysis-0.1.0a0.dist-info/METADATA
static_import_analysis-0.1.0a0.dist-info/WHEEL
static_import_analysis-0.1.0a0.dist-info/top_level.txt
static_import_analysis-0.1.0a0.dist-info/RECORD
