Metadata-Version: 2.4
Name: static-import-analysis
Version: 0.1.0a0
Summary: Static import analysis for Python projects: extract functions, classes, and imports by walking a project's AST.
Author-email: Jifeng Wu <jifengwu2k@gmail.com>
License-Expression: MIT
Project-URL: Homepage, https://github.com/jifengwu2k/static-import-analysis
Project-URL: Bug Tracker, https://github.com/jifengwu2k/static-import-analysis/issues
Classifier: Programming Language :: Python :: 2
Classifier: Programming Language :: Python :: 3
Classifier: Operating System :: OS Independent
Requires-Python: >=2
License-File: LICENSE
Requires-Dist: typing; python_version < "3.5"
Dynamic: license-file
